AioSpider/__init__.py
AioSpider/__version__
AioSpider/aioSpider.py
AioSpider/browser.py
AioSpider/constants.py
AioSpider/exceptions.py
AioSpider/settings.py
AioSpider/signal.py
AioSpider/cmd/__init__.py
AioSpider/cmd/args.py
AioSpider/cmd/cmd.py
AioSpider/cmd/create.py
AioSpider/cmd/make.py
AioSpider/cmd/options.py
AioSpider/cmd/server.py
AioSpider/cmd/test.py
AioSpider/core/__init__.py
AioSpider/core/concurrency_strategy.py
AioSpider/core/engine.py
AioSpider/core/patch.py
AioSpider/core/signals.py
AioSpider/core/task_queue.py
AioSpider/datamanager/__init__.py
AioSpider/datamanager/commit.py
AioSpider/datamanager/data_manager.py
AioSpider/datamanager/filter.py
AioSpider/datamanager/init.py
AioSpider/db/__init__.py
AioSpider/db/sql.py
AioSpider/db/async_db/__init__.py
AioSpider/db/async_db/async_abc.py
AioSpider/db/async_db/csv.py
AioSpider/db/async_db/lock.py
AioSpider/db/async_db/mongo.py
AioSpider/db/async_db/mysql.py
AioSpider/db/async_db/redis.py
AioSpider/db/async_db/sqlite.py
AioSpider/db/sync_db/__init__.py
AioSpider/db/sync_db/mongo.py
AioSpider/db/sync_db/mysql.py
AioSpider/db/sync_db/sqlite.py
AioSpider/db/sync_db/sync_abc.py
AioSpider/downloader/__init__.py
AioSpider/downloader/abc.py
AioSpider/downloader/aiohttp_module.py
AioSpider/downloader/downloader.py
AioSpider/downloader/requests_module.py
AioSpider/field/__init__.py
AioSpider/field/datefield.py
AioSpider/field/decimal.py
AioSpider/field/field.py
AioSpider/field/indexfield.py
AioSpider/field/intfield.py
AioSpider/field/textfield.py
AioSpider/field/validators.py
AioSpider/filter/__init__.py
AioSpider/filter/bloom.py
AioSpider/filter/dq.py
AioSpider/http/__init__.py
AioSpider/http/base.py
AioSpider/http/form.py
AioSpider/http/formRequest.py
AioSpider/http/request.py
AioSpider/http/response.py
AioSpider/loading/__init__.py
AioSpider/loading/load_browser.py
AioSpider/loading/load_database.py
AioSpider/loading/load_log.py
AioSpider/loading/load_middleware.py
AioSpider/loading/load_models.py
AioSpider_zly-2.0.0.dist-info/LICENSE
AioSpider_zly-2.0.0.dist-info/METADATA
AioSpider_zly-2.0.0.dist-info/WHEEL
AioSpider_zly-2.0.0.dist-info/entry_points.txt
AioSpider_zly-2.0.0.dist-info/top_level.txt
AioSpider_zly-2.0.0.dist-info/RECORD
