Metadata-Version: 2.1
Name: AioSpider-zly
Version: 2.0.0
Summary: 高并发异步爬虫框架
Home-page: https://github.com/zly717216/AioSpider
Author: zly717216
Author-email: zly717216@qq.com
Maintainer: zly
License: MIT
Keywords: 异步网页抓取,网络爬虫,异步爬虫,Python 异步抓取,数据提取,网络数据挖掘,异步爬虫框架,网络爬取工具,数据采集,数据挖掘工具
Classifier: Development Status :: 5 - Production/Stable
Classifier: Operating System :: OS Independent
Classifier: Programming Language :: Python :: 3.8
Classifier: Programming Language :: Python :: 3.9
Classifier: Programming Language :: Python :: 3.10
Classifier: Programming Language :: Python :: 3.11
Classifier: Programming Language :: Python :: Implementation :: CPython
Classifier: Topic :: Software Development :: Libraries :: Application Frameworks
Classifier: Topic :: Software Development :: Libraries :: Python Modules
Requires-Python: >=3.7
License-File: LICENSE
Requires-Dist: idna ==3.6
Requires-Dist: six ==1.16.0
Requires-Dist: typing-extensions ==4.9.0
Requires-Dist: aiocsv ==1.2.4
Requires-Dist: aiofiles ==23.2.1
Requires-Dist: aiohttp ==3.9.1
Requires-Dist: aiomysql ==0.2.0
Requires-Dist: aioredis ==2.0.1
Requires-Dist: aiosqlite ==0.19.0
Requires-Dist: motor ==3.3.1
Requires-Dist: beautifulsoup4 ==4.12.2
Requires-Dist: bitarray ==2.8.2
Requires-Dist: chardet ==3.0.4
Requires-Dist: cchardet ==2.1.7
Requires-Dist: ddddocr ==1.4.8
Requires-Dist: loguru ==0.7.2
Requires-Dist: lxml ==4.9.3
Requires-Dist: pydash ==7.0.6
Requires-Dist: opencv-python ==4.8.1.78
Requires-Dist: pillow ==9.5.0
Requires-Dist: openpyxl ==3.1.2
Requires-Dist: pycryptodome ==3.19.0
Requires-Dist: PyExecJS ==1.5.1
Requires-Dist: pymongo ==4.5.0
Requires-Dist: pymysql ==1.1.0
Requires-Dist: redis ==5.0.1
Requires-Dist: requests ==2.28.1
Requires-Dist: rsa ==4.9
Requires-Dist: selenium ==4.14.0
Requires-Dist: playwright ==1.39.0
Requires-Dist: tabula-py ==2.8.2
Requires-Dist: tqdm ==4.66.1
Requires-Dist: w3lib ==2.1.2
Requires-Dist: dataframe-image ==0.2.2
Requires-Dist: pandas ==2.1.2
Requires-Dist: pycryptodome
